fixed_mcp_protocol_web.py
server.py
polardb_openapi_mcp_server-0.2.6.dist-info/METADATA
polardb_openapi_mcp_server-0.2.6.dist-info/WHEEL
polardb_openapi_mcp_server-0.2.6.dist-info/entry_points.txt
polardb_openapi_mcp_server-0.2.6.dist-info/top_level.txt
polardb_openapi_mcp_server-0.2.6.dist-info/RECORD
