Metadata-Version: 2.4
Name: polardb-openapi-mcp-server
Version: 0.2.6
Summary: MCP server for Alibaba Cloud PolarDB OpenAPI management with slow log analysis and performance monitoring
Requires-Python: >=3.12
Requires-Dist: alibabacloud_polardb20170801>=5.6.0
Requires-Dist: alibabacloud_vpc20160428>=4.5.0
Requires-Dist: alibabacloud_das20200116>=1.0.0
Requires-Dist: python-dotenv
Requires-Dist: starlette
Requires-Dist: uvicorn
Requires-Dist: mcp[cli]>=1.6.0
Requires-Dist: mysql-connector-python
Requires-Dist: sqlparse
Requires-Dist: pytz
